{"is_source_file": true, "format": "Python", "description": "This file defines a Django app configuration class for 'api', responsible for initializing database repair and seeding demo data when the application is ready. It sets up automatic repair of SQLite migration drift and conditionally seeds demo data if the database is empty, with robust error handling to avoid startup failures.", "external_files": ["django.apps", "django.core.management", "django.db"], "external_methods": ["call_command", "Defect.objects.count()"], "published": ["ApiConfig"], "classes": [{"name": "ApiConfig", "description": "A Django AppConfig subclass that runs database repair and seed logic during app startup."}], "methods": [{"name": "None ready(self)", "description": "Initializes database consistency checks and seeds demo data when appropriate during application startup.", "scope": "ApiConfig", "scopeKind": "class"}], "calls": ["call_command", "Defect.objects.count()"], "search-terms": ["ApiConfig", "ready method", "auto-seeding", "SQLite migration repair", "Django app configuration", "database initialization", "database seed automation"], "state": 2, "file_id": 46, "knowledge_revision": 162, "git_revision": "634f8d0ed2a2055489165fd3376d80360a4c5430", "ctags": [{"_type": "tag", "name": "ApiConfig", "path": "/home/kavia/workspace/code-generation/quality-defect-management-system-3326-3336/backend/api/apps.py", "pattern": "/^class ApiConfig(AppConfig):$/", "language": "Python", "kind": "class"}, {"_type": "tag", "name": "default_auto_field", "path": "/home/kavia/workspace/code-generation/quality-defect-management-system-3326-3336/backend/api/apps.py", "pattern": "/^    default_auto_field = \"django.db.models.BigAutoField\"$/", "language": "Python", "kind": "variable", "scope": "ApiConfig", "scopeKind": "class"}, {"_type": "tag", "name": "logger", "path": "/home/kavia/workspace/code-generation/quality-defect-management-system-3326-3336/backend/api/apps.py", "pattern": "/^logger = logging.getLogger(__name__)$/", "language": "Python", "kind": "variable"}, {"_type": "tag", "name": "name", "path": "/home/kavia/workspace/code-generation/quality-defect-management-system-3326-3336/backend/api/apps.py", "pattern": "/^    name = \"api\"$/", "language": "Python", "kind": "variable", "scope": "ApiConfig", "scopeKind": "class"}, {"_type": "tag", "name": "ready", "path": "/home/kavia/workspace/code-generation/quality-defect-management-system-3326-3336/backend/api/apps.py", "pattern": "/^    def ready(self) -> None:$/", "language": "Python", "typeref": "typename:None", "kind": "member", "signature": "(self)", "scope": "ApiConfig", "scopeKind": "class"}], "hash": "763a1af6fa449a200711884339720f0e", "format-version": 4, "code-base-name": "backend", "filename": "backend/api/apps.py", "fields": [{"name": "default_auto_field = \"django.db.models.BigAutoField\"", "scope": "ApiConfig", "scopeKind": "class", "description": "unavailable"}, {"name": "logger = logging.getLogger(__name__)", "scope": "", "scopeKind": "", "description": "unavailable"}, {"name": "name = \"api\"", "scope": "ApiConfig", "scopeKind": "class", "description": "unavailable"}], "revision_history": [{"162": "634f8d0ed2a2055489165fd3376d80360a4c5430"}]}